arrus-0.7.0.data/purelib/arrus/DBARLite.dll
arrus-0.7.0.data/purelib/arrus/HV256.dll
arrus-0.7.0.data/purelib/arrus/Us4OEM.dll
arrus-0.7.0.data/purelib/arrus/Us4RDBAR.dll
arrus-0.7.0.data/purelib/arrus/Us4RPSC.dll
arrus-0.7.0.data/purelib/arrus/__init__.py
arrus-0.7.0.data/purelib/arrus/_py_core.pyd
arrus-0.7.0.data/purelib/arrus/arrus-core.dll
arrus-0.7.0.data/purelib/arrus/boost_atomic.dll
arrus-0.7.0.data/purelib/arrus/boost_chrono.dll
arrus-0.7.0.data/purelib/arrus/boost_container.dll
arrus-0.7.0.data/purelib/arrus/boost_context.dll
arrus-0.7.0.data/purelib/arrus/boost_contract.dll
arrus-0.7.0.data/purelib/arrus/boost_coroutine.dll
arrus-0.7.0.data/purelib/arrus/boost_date_time.dll
arrus-0.7.0.data/purelib/arrus/boost_fiber.dll
arrus-0.7.0.data/purelib/arrus/boost_fiber_numa.dll
arrus-0.7.0.data/purelib/arrus/boost_filesystem.dll
arrus-0.7.0.data/purelib/arrus/boost_graph.dll
arrus-0.7.0.data/purelib/arrus/boost_iostreams.dll
arrus-0.7.0.data/purelib/arrus/boost_locale.dll
arrus-0.7.0.data/purelib/arrus/boost_log.dll
arrus-0.7.0.data/purelib/arrus/boost_log_setup.dll
arrus-0.7.0.data/purelib/arrus/boost_math_c99.dll
arrus-0.7.0.data/purelib/arrus/boost_math_c99f.dll
arrus-0.7.0.data/purelib/arrus/boost_math_c99l.dll
arrus-0.7.0.data/purelib/arrus/boost_math_tr1.dll
arrus-0.7.0.data/purelib/arrus/boost_math_tr1f.dll
arrus-0.7.0.data/purelib/arrus/boost_math_tr1l.dll
arrus-0.7.0.data/purelib/arrus/boost_prg_exec_monitor.dll
arrus-0.7.0.data/purelib/arrus/boost_program_options.dll
arrus-0.7.0.data/purelib/arrus/boost_random.dll
arrus-0.7.0.data/purelib/arrus/boost_regex.dll
arrus-0.7.0.data/purelib/arrus/boost_serialization.dll
arrus-0.7.0.data/purelib/arrus/boost_stacktrace_noop.dll
arrus-0.7.0.data/purelib/arrus/boost_stacktrace_windbg.dll
arrus-0.7.0.data/purelib/arrus/boost_stacktrace_windbg_cached.dll
arrus-0.7.0.data/purelib/arrus/boost_system.dll
arrus-0.7.0.data/purelib/arrus/boost_thread.dll
arrus-0.7.0.data/purelib/arrus/boost_timer.dll
arrus-0.7.0.dist-info/METADATA
arrus-0.7.0.dist-info/WHEEL
arrus-0.7.0.dist-info/top_level.txt
arrus-0.7.0.dist-info/RECORD
